{
    "os": "Linux-4.19.112+-x86_64-with-Ubuntu-18.04-bionic",
    "python": "3.7.10",
    "heartbeatAt": "2021-04-24T18:24:16.937139",
    "startedAt": "2021-04-24T18:24:13.879924",
    "docker": null,
    "gpu": "Tesla P100-PCIE-16GB",
    "gpu_count": 1,
    "cpu_count": 2,
    "cuda": "11.0.228",
    "args": [
        "--dataroot",
        "./datasets/nemsimu2nemreal",
        "--name",
        "nemsimu2nemreal",
        "--model",
        "cycle_gan",
        "--continue_train",
        "--epoch_count",
        "183"
    ],
    "state": "running",
    "program": "train.py",
    "codePath": "train.py",
    "host": "0bed45e1ee64",
    "username": "root",
    "executable": "/usr/bin/python3"
}
